DESCRIPTION.rst
LICENSE.txt
README.rst
setup.py
diversipy/__init__.py
diversipy/distance.py
diversipy/hycusampling.py
diversipy/indicator.py
diversipy/subset.py
diversipy.egg-info/PKG-INFO
diversipy.egg-info/SOURCES.txt
diversipy.egg-info/dependency_links.txt
diversipy.egg-info/requires.txt
diversipy.egg-info/top_level.txt