Metadata-Version: 1.1
Name: diversipy
Version: 0.3
Summary: Sample in hypercubes, select diverse subsets, and evaluate diversity indicators
Home-page: https://ls11-www.cs.tu-dortmund.de/people/swessing/diversipy/doc/
Author: Simon Wessing
Author-email: simon.wessing@tu-dortmund.de
License: BSD
Keywords: diversity uniformity discrepancy distance hypercube subset doe dace space-filling design experiments
Platform: UNKNOWN
Classifier: Development Status :: 4 - Beta
Classifier: Intended Audience :: Science/Research
Classifier: Topic :: Scientific/Engineering
Classifier: Topic :: Scientific/Engineering :: Mathematics
Classifier: Topic :: Scientific/Engineering :: Artificial Intelligence
Classifier: License :: OSI Approved :: BSD License
Classifier: Programming Language :: Python :: 2
Classifier: Programming Language :: Python :: 2.7
Classifier: Programming Language :: Python :: 3
Classifier: Programming Language :: Python :: 3.4
Requires: numpy
